{"cameraMode":{"drawMode":0,"name":"Shaded","section":"Shading Mode"},"sceneLighting":false,"audioPlay":false,"sceneViewState":{"m_AlwaysRefresh":false,"showFog":true,"showSkybox":false,"showFlares":true,"showImageEffects":true,"showParticleSystems":true,"showVisualEffectGraphs":true,"m_FxEnabled":true},"in2DMode":false,"pivot":{"x":0.6455733776092529,"y":11.132415771484375,"z":-4.413508415222168},"rotation":{"x":0.0813257247209549,"y":0.2585717439651489,"z":-0.021851221099495889,"w":0.9623202681541443},"size":6.303435802459717,"orthographic":false}